AthenaTwitchLib/__init__.py
AthenaTwitchLib/logger.py
AthenaTwitchLib/string_formatting.py
AthenaTwitchLib/api/__init__.py
AthenaTwitchLib/irc/__init__.py
AthenaTwitchLib/irc/bot.py
AthenaTwitchLib/irc/irc_connection.py
AthenaTwitchLib/irc/irc_connection_protocol.py
AthenaTwitchLib/irc/message_context.py
AthenaTwitchLib/irc/data/__init__.py
AthenaTwitchLib/irc/data/enums.py
AthenaTwitchLib/irc/data/regex.py
AthenaTwitchLib/irc/data/sql.py
AthenaTwitchLib/irc/logic/__init__.py
AthenaTwitchLib/irc/logic/_logic.py
AthenaTwitchLib/irc/logic/commands.py
AthenaTwitchLib/irc/logic/commands_sqlite.py
AthenaTwitchLib/irc/logic/tasks.py
AthenaTwitchLib/irc/tags/__init__.py
AthenaTwitchLib/irc/tags/_tags.py
AthenaTwitchLib/irc/tags/tags_clearchat.py
AthenaTwitchLib/irc/tags/tags_clearmsg.py
AthenaTwitchLib/irc/tags/tags_globaluserstate.py
AthenaTwitchLib/irc/tags/tags_notice.py
AthenaTwitchLib/irc/tags/tags_privmsg.py
AthenaTwitchLib/irc/tags/tags_roomstate.py
AthenaTwitchLib/irc/tags/tags_usernotice.py
AthenaTwitchLib/irc/tags/tags_userstate.py
AthenaTwitchLib-0.9.1.dist-info/LICENSE
AthenaTwitchLib-0.9.1.dist-info/METADATA
AthenaTwitchLib-0.9.1.dist-info/WHEEL
AthenaTwitchLib-0.9.1.dist-info/top_level.txt
AthenaTwitchLib-0.9.1.dist-info/RECORD
