Metadata-Version: 2.1
Name: AthenaTwitchLib
Version: 0.9.1
Summary: A library to create Twitch Chat Bots and connect to the Twitch Helix API.
Home-page: https://github.com/Athena-Chaos-Driven-Code/AthenaTwitchLib
Author: Andreas Sas
Author-email: 
License: GPLv3
Project-URL: Bug Tracker, https://github.com/Athena-Chaos-Driven-Code/AthenaTwitchLib/issues
Requires-Python: >=3.11
License-File: LICENSE
Requires-Dist: AthenaLib (>=2.3.0)
Requires-Dist: AthenaColor (>=7.0.1)
